{
  "clean": [
    {
      "scenario": "clean",
      "regime": "baseline",
      "metric_path": "metric/case39/metric_event_trigger_clean_tau_-1.0_mode_0_0.03_1.1.npy",
      "tau_verify": -1.0,
      "total_alarms": 819,
      "total_triggers": 819,
      "recovery_error_count": 0,
      "recovery_error_rate_among_alarms": 0.0,
      "recovery_error_policy": "skip",
      "backend_metric_success_count": 761,
      "backend_metric_fail_count": 58,
      "backend_metric_fail_rate_among_triggers": 0.07081807081807082,
      "backend_metric_fail_rate_among_alarms": 0.07081807081807082,
      "backend_mtd_fail_count": 789,
      "backend_mtd_fail_rate_among_triggers": 0.9633699633699634,
      "backend_mtd_fail_rate_among_alarms": 0.9633699633699634,
      "stage_one_time_success_only_mean": 8.044997102902776,
      "stage_one_time_denominator": 819,
      "stage_one_time_nan_count": 0,
      "stage_two_time_success_only_mean": 1.3620959259797074,
      "stage_two_time_denominator": 819,
      "stage_two_time_nan_count": 0,
      "delta_cost_one_success_only_mean": 0.8504881125947578,
      "delta_cost_one_denominator": 762,
      "delta_cost_one_nan_count": 57,
      "delta_cost_two_success_only_mean": 0.7842876342352035,
      "delta_cost_two_denominator": 761,
      "delta_cost_two_nan_count": 58,
      "legacy_false_alarm_rate": 0.11665004985044865,
      "legacy_trigger_rate": 1.0,
      "legacy_useless_mtd_rate": 0.11665004985044865,
      "legacy_fail_per_alarm": 0.9633699633699634,
      "legacy_stage_one_time_per_alarm": 8.044997102902776,
      "legacy_stage_two_time_per_alarm": 1.3620959259797074,
      "legacy_delta_cost_one_per_alarm": 0.7912966322310201,
      "legacy_delta_cost_two_per_alarm": 0.7287458970121977
    },
    {
      "scenario": "clean",
      "regime": "main",
      "metric_path": "metric/case39/metric_event_trigger_clean_tau_0.013319196253_mode_0_0.03_1.1.npy",
      "tau_verify": 0.013319196253,
      "total_alarms": 819,
      "total_triggers": 754,
      "recovery_error_count": 0,
      "recovery_error_rate_among_alarms": 0.0,
      "recovery_error_policy": "skip",
      "backend_metric_success_count": 705,
      "backend_metric_fail_count": 49,
      "backend_metric_fail_rate_among_triggers": 0.0649867374005305,
      "backend_metric_fail_rate_among_alarms": 0.05982905982905983,
      "backend_mtd_fail_count": 739,
      "backend_mtd_fail_rate_among_triggers": 0.980106100795756,
      "backend_mtd_fail_rate_among_alarms": 0.9023199023199023,
      "stage_one_time_success_only_mean": 8.144084416902983,
      "stage_one_time_denominator": 754,
      "stage_one_time_nan_count": 0,
      "stage_two_time_success_only_mean": 0.6988369599577603,
      "stage_two_time_denominator": 754,
      "stage_two_time_nan_count": 0,
      "delta_cost_one_success_only_mean": 0.7945781582943832,
      "delta_cost_one_denominator": 705,
      "delta_cost_one_nan_count": 49,
      "delta_cost_two_success_only_mean": 0.7515260295055571,
      "delta_cost_two_denominator": 705,
      "delta_cost_two_nan_count": 49,
      "legacy_false_alarm_rate": 0.11665004985044865,
      "legacy_trigger_rate": 0.9206349206349206,
      "legacy_useless_mtd_rate": 0.10739210938612734,
      "legacy_fail_per_alarm": 0.9023199023199023,
      "legacy_stage_one_time_per_alarm": 7.497728510799571,
      "legacy_stage_two_time_per_alarm": 0.6433737091674618,
      "legacy_delta_cost_one_per_alarm": 0.6839775355281321,
      "legacy_delta_cost_two_per_alarm": 0.6469180107465419
    },
    {
      "scenario": "clean",
      "regime": "strict",
      "metric_path": "metric/case39/metric_event_trigger_clean_tau_0.016153267226_mode_0_0.03_1.1.npy",
      "tau_verify": 0.016153267226,
      "total_alarms": 819,
      "total_triggers": 676,
      "recovery_error_count": 0,
      "recovery_error_rate_among_alarms": 0.0,
      "recovery_error_policy": "skip",
      "backend_metric_success_count": 633,
      "backend_metric_fail_count": 43,
      "backend_metric_fail_rate_among_triggers": 0.06360946745562131,
      "backend_metric_fail_rate_among_alarms": 0.052503052503052504,
      "backend_mtd_fail_count": 663,
      "backend_mtd_fail_rate_among_triggers": 0.9807692307692307,
      "backend_mtd_fail_rate_among_alarms": 0.8095238095238095,
      "stage_one_time_success_only_mean": 8.347419078533466,
      "stage_one_time_denominator": 676,
      "stage_one_time_nan_count": 0,
      "stage_two_time_success_only_mean": 0.6599895569699756,
      "stage_two_time_denominator": 676,
      "stage_two_time_nan_count": 0,
      "delta_cost_one_success_only_mean": 0.733448085623678,
      "delta_cost_one_denominator": 633,
      "delta_cost_one_nan_count": 43,
      "delta_cost_two_success_only_mean": 0.7121661103615922,
      "delta_cost_two_denominator": 633,
      "delta_cost_two_nan_count": 43,
      "legacy_false_alarm_rate": 0.11665004985044865,
      "legacy_trigger_rate": 0.8253968253968254,
      "legacy_useless_mtd_rate": 0.09628258082894174,
      "legacy_fail_per_alarm": 0.8095238095238095,
      "legacy_stage_one_time_per_alarm": 6.889933207678417,
      "legacy_stage_two_time_per_alarm": 0.5447532851180751,
      "legacy_delta_cost_one_per_alarm": 0.5668774581193995,
      "legacy_delta_cost_two_per_alarm": 0.550428751964454
    }
  ],
  "attack": [
    {
      "scenario": "attack",
      "regime": "baseline",
      "metric_path": "metric/case39/metric_event_trigger_tau_-1.0_mode_0_0.03_1.1.npy",
      "tau_verify": -1.0,
      "total_alarms": 292,
      "total_triggers": 292,
      "recovery_error_count": 0,
      "recovery_error_rate_among_alarms": 0.0,
      "recovery_error_policy": "count_as_non_trigger_non_skip",
      "backend_metric_success_count": 0,
      "backend_metric_fail_count": 292,
      "backend_metric_fail_rate_among_triggers": 1.0,
      "backend_metric_fail_rate_among_alarms": 1.0,
      "backend_mtd_fail_count": 229,
      "backend_mtd_fail_rate_among_triggers": 0.7842465753424658,
      "backend_mtd_fail_rate_among_alarms": 0.7842465753424658,
      "stage_one_time_success_only_mean": 6.39966562594453,
      "stage_one_time_denominator": 292,
      "stage_one_time_nan_count": 0,
      "stage_two_time_success_only_mean": 12.574489570643804,
      "stage_two_time_denominator": 292,
      "stage_two_time_nan_count": 0,
      "delta_cost_one_success_only_mean": NaN,
      "delta_cost_one_denominator": 0,
      "delta_cost_one_nan_count": 292,
      "delta_cost_two_success_only_mean": NaN,
      "delta_cost_two_denominator": 0,
      "delta_cost_two_nan_count": 292,
      "overall_arr": 1.0
    },
    {
      "scenario": "attack",
      "regime": "main",
      "metric_path": "metric/case39/metric_event_trigger_tau_0.013319196253_mode_0_0.03_1.1.npy",
      "tau_verify": 0.013319196253,
      "total_alarms": 292,
      "total_triggers": 290,
      "recovery_error_count": 0,
      "recovery_error_rate_among_alarms": 0.0,
      "recovery_error_policy": "count_as_non_trigger_non_skip",
      "backend_metric_success_count": 0,
      "backend_metric_fail_count": 290,
      "backend_metric_fail_rate_among_triggers": 1.0,
      "backend_metric_fail_rate_among_alarms": 0.9931506849315068,
      "backend_mtd_fail_count": 228,
      "backend_mtd_fail_rate_among_triggers": 0.7862068965517242,
      "backend_mtd_fail_rate_among_alarms": 0.7808219178082192,
      "stage_one_time_success_only_mean": 6.413142124537764,
      "stage_one_time_denominator": 290,
      "stage_one_time_nan_count": 0,
      "stage_two_time_success_only_mean": 12.54535091087736,
      "stage_two_time_denominator": 290,
      "stage_two_time_nan_count": 0,
      "delta_cost_one_success_only_mean": NaN,
      "delta_cost_one_denominator": 0,
      "delta_cost_one_nan_count": 290,
      "delta_cost_two_success_only_mean": NaN,
      "delta_cost_two_denominator": 0,
      "delta_cost_two_nan_count": 290,
      "overall_arr": 0.9931506849315068
    },
    {
      "scenario": "attack",
      "regime": "strict",
      "metric_path": "metric/case39/metric_event_trigger_tau_0.016153267226_mode_0_0.03_1.1.npy",
      "tau_verify": 0.016153267226,
      "total_alarms": 292,
      "total_triggers": 288,
      "recovery_error_count": 0,
      "recovery_error_rate_among_alarms": 0.0,
      "recovery_error_policy": "count_as_non_trigger_non_skip",
      "backend_metric_success_count": 0,
      "backend_metric_fail_count": 288,
      "backend_metric_fail_rate_among_triggers": 1.0,
      "backend_metric_fail_rate_among_alarms": 0.9863013698630136,
      "backend_mtd_fail_count": 226,
      "backend_mtd_fail_rate_among_triggers": 0.7847222222222222,
      "backend_mtd_fail_rate_among_alarms": 0.773972602739726,
      "stage_one_time_success_only_mean": 6.424032412469387,
      "stage_one_time_denominator": 288,
      "stage_one_time_nan_count": 0,
      "stage_two_time_success_only_mean": 12.632471403314007,
      "stage_two_time_denominator": 288,
      "stage_two_time_nan_count": 0,
      "delta_cost_one_success_only_mean": NaN,
      "delta_cost_one_denominator": 0,
      "delta_cost_one_nan_count": 288,
      "delta_cost_two_success_only_mean": NaN,
      "delta_cost_two_denominator": 0,
      "delta_cost_two_nan_count": 288,
      "overall_arr": 0.9863013698630136
    }
  ]
}